Metadata-Version: 2.1
Name: mode-streaming
Version: 0.4.0
Summary: AsyncIO Service-based programming
Author-email: Ask Solem Hoel <ask@robinhood.com>
Maintainer-email: William Barnhart <williambbarnhart@gmail.com>
Project-URL: Homepage, https://github.com/faust-streaming/mode
Project-URL: Documentation, https://faust-streaming.github.io/mode/
Project-URL: Repository, https://github.com/faust-streaming/mode
Keywords: asyncio,service,bootsteps,graph,coroutine
Classifier: Framework :: AsyncIO
Classifier: Development Status :: 5 - Production/Stable
Classifier: License :: OSI Approved :: BSD License
Classifier: Programming Language :: Python :: 3 :: Only
Classifier: Programming Language :: Python :: 3.8
Classifier: Programming Language :: Python :: 3.9
Classifier: Programming Language :: Python :: 3.10
Classifier: Programming Language :: Python :: 3.11
Classifier: Programming Language :: Python :: 3.12
Classifier: Programming Language :: Python :: Implementation :: CPython
Classifier: Programming Language :: Python :: Implementation :: PyPy
Classifier: Operating System :: POSIX
Classifier: Operating System :: Microsoft :: Windows
Classifier: Operating System :: MacOS :: MacOS X
Classifier: Operating System :: Unix
Classifier: Environment :: No Input/Output (Daemon)
Classifier: Framework :: AsyncIO
Classifier: Intended Audience :: Developers
Requires-Python: >=3.8
License-File: LICENSE
License-File: AUTHORS
Requires-Dist: colorlog <7.0.0,>=6.0.0
Requires-Dist: croniter <3.0.0,>=2.0.0
Requires-Dist: mypy-extensions
Provides-Extra: eventlet
Requires-Dist: faust-aioeventlet ; extra == 'eventlet'
Requires-Dist: dnspython ; extra == 'eventlet'
Provides-Extra: gevent
Requires-Dist: asyncio-gevent ~=0.2 ; extra == 'gevent'
Provides-Extra: uvloop
Requires-Dist: uvloop >=0.19.0 ; extra == 'uvloop'
